ibm_db_django/__init__.py
ibm_db_django/base.py
ibm_db_django/client.py
ibm_db_django/compiler.py
ibm_db_django/creation.py
ibm_db_django/introspection.py
ibm_db_django/jybase.py
ibm_db_django/operations.py
ibm_db_django/pybase.py
ibm_db_django/query.py
ibm_db_django/schemaEditor.py
ibm_db_django-1.3.0.0.data/data/CHANGES
ibm_db_django-1.3.0.0.data/data/LICENSE
ibm_db_django-1.3.0.0.data/data/README.md
ibm_db_django-1.3.0.0.dist-info/LICENSE
ibm_db_django-1.3.0.0.dist-info/METADATA
ibm_db_django-1.3.0.0.dist-info/WHEEL
ibm_db_django-1.3.0.0.dist-info/dependency_links.txt
ibm_db_django-1.3.0.0.dist-info/entry_points.txt
ibm_db_django-1.3.0.0.dist-info/top_level.txt
ibm_db_django-1.3.0.0.dist-info/RECORD
